dobpy/__init__.py
dobpy/dob.py
dobpy-0.1.dist-info/METADATA
dobpy-0.1.dist-info/WHEEL
dobpy-0.1.dist-info/top_level.txt
dobpy-0.1.dist-info/zip-safe
dobpy-0.1.dist-info/RECORD
