Metadata-Version: 2.1
Name: dobpy
Version: 0.1
Summary: A "post styled database"
Home-page: http://github.com/owocean/dob
Author: owocean
Author-email: imdownunderthere@gmail.com
License: MIT
Platform: UNKNOWN
